README.md
setup.cfg
setup.py
slackbot_cloudgenix/__init__.py
slackbot_cloudgenix/apps.py
slackbot_cloudgenix/helpers.py
slackbot_cloudgenix/metrics.py
slackbot_cloudgenix/sites.py
slackbot_cloudgenix/topology.py
slackbot_cloudgenix.egg-info/PKG-INFO
slackbot_cloudgenix.egg-info/SOURCES.txt
slackbot_cloudgenix.egg-info/dependency_links.txt
slackbot_cloudgenix.egg-info/requires.txt
slackbot_cloudgenix.egg-info/top_level.txt