Metadata-Version: 2.1
Name: slackbot-cloudgenix
Version: 0.5.0b2
Summary: CloudGenix AppFabric plugin functions for lins05/slackbot.
Home-page: https://github.com/ebob9/slackbot-cloudgenix
Author: Aaron Edwards
Author-email: cloudgenix-slackbot@ebob9.com
License: MIT
Platform: UNKNOWN
Classifier: Development Status :: 4 - Beta
Classifier: Intended Audience :: Developers
Classifier: License :: OSI Approved :: MIT License
Classifier: Programming Language :: Python :: 3.6
Classifier: Programming Language :: Python :: 3.7
Classifier: Programming Language :: Python :: 3.8
